citlalicue/__init__.py
citlalicue/citlalicue.py
citlalicue/detrending.py
citlalicue-0.7.1.dist-info/LICENSE
citlalicue-0.7.1.dist-info/METADATA
citlalicue-0.7.1.dist-info/WHEEL
citlalicue-0.7.1.dist-info/top_level.txt
citlalicue-0.7.1.dist-info/RECORD
