Metadata-Version: 2.1
Name: citlalicue
Version: 0.7.1
Summary: Create stellar light curves!
Home-page: https://github.com/oscaribv/citlalicue
Author: Oscar Barragán
Author-email: oscaribv@gmail.com
Classifier: Programming Language :: Python :: 3
Classifier: License :: OSI Approved :: GNU General Public License v3 (GPLv3)
Classifier: Operating System :: OS Independent
Requires-Python: >=3
License-File: LICENSE
Requires-Dist: numpy
Requires-Dist: matplotlib
Requires-Dist: scipy
Requires-Dist: pytransit
Requires-Dist: george
Requires-Dist: emcee
Requires-Dist: celerite
Requires-Dist: corner
Requires-Dist: lightkurve
